nsv/__init__.py
nsv/core.py
nsv/reader.py
nsv/util.py
nsv/writer.py
nsv-0.2.2.dist-info/licenses/LICENSE
tests/__init__.py
tests/test_benchmarks.py
tests/test_composition.py
tests/test_dump.py
tests/test_edge_cases.py
tests/test_enumeration.py
tests/test_escape.py
tests/test_incremental.py
tests/test_load.py
tests/test_spill.py
tests/test_utils.py
nsv-0.2.2.dist-info/METADATA
nsv-0.2.2.dist-info/WHEEL
nsv-0.2.2.dist-info/top_level.txt
nsv-0.2.2.dist-info/RECORD
