Metadata-Version: 2.4
Name: nsv
Version: 0.2.2
Summary: Python implementation of the NSV (Newline-Separated Values) format
Home-page: https://github.com/namingbe/nsv-python
Author: naming
Author-email: 
Project-URL: Bug Reports, https://github.com/namingbe/nsv-python/issues
Project-URL: Source, https://github.com/namingbe/nsv-python
Keywords: nsv csv data format parser
Classifier: Development Status :: 3 - Alpha
Classifier: Intended Audience :: Developers
Classifier: Topic :: Software Development :: Libraries :: Python Modules
Classifier: Topic :: Text Processing
Classifier: License :: OSI Approved :: MIT License
Classifier: Programming Language :: Python :: 3
Classifier: Programming Language :: Python :: 3.6
Classifier: Programming Language :: Python :: 3.7
Classifier: Programming Language :: Python :: 3.8
Classifier: Programming Language :: Python :: 3.9
Classifier: Programming Language :: Python :: 3.10
Classifier: Programming Language :: Python :: 3.11
Classifier: Programming Language :: Python :: 3.12
Classifier: Operating System :: OS Independent
Requires-Python: >=3.6
License-File: LICENSE
Provides-Extra: pandas
Requires-Dist: pandas; extra == "pandas"
Dynamic: author
Dynamic: classifier
Dynamic: description
Dynamic: description-content-type
Dynamic: home-page
Dynamic: keywords
Dynamic: license-file
Dynamic: project-url
Dynamic: provides-extra
Dynamic: requires-python
Dynamic: summary
